[
  {
    "id": 1,
    "character": "完",
    "meanings": "complete; whole",
    "onyomi": "カン",
    "kunyomi": "まった(く)",
    "hiragana_reading": "かん",
    "pitch_accent": "1",
    "han_viet": "hoan",
    "jlpt_level": "N2",
    "frequency": 1856,
    "notes": "Core kanji for words about completion."
  },
  {
    "id": 2,
    "character": "全",
    "meanings": "whole; all",
    "onyomi": "ゼン",
    "kunyomi": "すべ(て)",
    "hiragana_reading": "ぜん",
    "pitch_accent": "1",
    "han_viet": "toan",
    "jlpt_level": "N3",
    "frequency": 222,
    "notes": "Often appears in compounds expressing completeness."
  }
]
